boac/__init__.py
boac/_version.py
boac-0.0.2.dist-info/METADATA
boac-0.0.2.dist-info/WHEEL
boac-0.0.2.dist-info/licenses/LICENSE
boac-0.0.2.dist-info/RECORD
